rubpy/__init__.py
rubpy/client.py
rubpy/exceptions.py
rubpy/filters.py
rubpy/handlers.py
rubpy/network.py
rubpy/sync.py
rubpy/utils.py
rubpy/bot/__init__.py
rubpy/bot/bot.py
rubpy/bot/dict_like.py
rubpy/bot/enums.py
rubpy/bot/exceptions.py
rubpy/bot/filters.py
rubpy/bot/models.py
rubpy/crypto/__init__.py
rubpy/crypto/crypto.py
rubpy/enums/__init__.py
rubpy/enums/chat_access_type.py
rubpy/enums/chat_action.py
rubpy/enums/chat_type.py
rubpy/enums/message_media_type.py
rubpy/enums/parse_mode.py
rubpy/enums/poll_type.py
rubpy/enums/reaction_type.py
rubpy/enums/report_type.py
rubpy/methods/__init__.py
rubpy/methods/advanced/__init__.py
rubpy/methods/advanced/build.py
rubpy/methods/advanced/voice_chat_player.py
rubpy/methods/auth/__init__.py
rubpy/methods/auth/register_device.py
rubpy/methods/auth/send_code.py
rubpy/methods/auth/sign_in.py
rubpy/methods/channels/__init__.py
rubpy/methods/channels/add_channel.py
rubpy/methods/channels/add_channel_members.py
rubpy/methods/channels/ban_channel_member.py
rubpy/methods/channels/channel_preview_by_join_link.py
rubpy/methods/channels/check_channel_username.py
rubpy/methods/channels/create_channel_voice_chat.py
rubpy/methods/channels/discard_channel_voice_chat.py
rubpy/methods/channels/edit_channel_info.py
rubpy/methods/channels/get_banned_group_members.py
rubpy/methods/channels/get_channel_admin_access_list.py
rubpy/methods/channels/get_channel_admin_members.py
rubpy/methods/channels/get_channel_all_members.py
rubpy/methods/channels/get_channel_info.py
rubpy/methods/channels/get_channel_link.py
rubpy/methods/channels/join_channel_action.py
rubpy/methods/channels/join_channel_by_link.py
rubpy/methods/channels/remove_channel.py
rubpy/methods/channels/seen_channel_messages.py
rubpy/methods/channels/set_channel_link.py
rubpy/methods/channels/set_channel_voice_chat_setting.py
rubpy/methods/channels/update_channel_username.py
rubpy/methods/chats/__init__.py
rubpy/methods/chats/delete_avatar.py
rubpy-7.3.3.dist-info/licenses/LICENSE
rubpy-7.3.3.dist-info/METADATA
rubpy-7.3.3.dist-info/WHEEL
rubpy-7.3.3.dist-info/top_level.txt
rubpy-7.3.3.dist-info/RECORD
