Metadata-Version: 2.4
Name: rubpy
Version: 7.3.3
Summary: Elegant, modern and asynchronous Rubika API framework in Python for users and bots
Home-page: https://github.com/shayanheidari01/rubika
Author: Shayan Heidari
Author-email: contact@shayanheidari.info
Keywords: rubika,rubpy,chat,bot,robot,asyncio
Classifier: Programming Language :: Python :: 3.7
Classifier: Programming Language :: Python :: 3.8
Classifier: Programming Language :: Python :: 3.9
Classifier: Programming Language :: Python :: 3.10
Classifier: Programming Language :: Python :: 3.11
Classifier: Programming Language :: Python :: 3.12
Classifier: Programming Language :: Python :: 3.13
Classifier: License :: OSI Approved :: GNU Lesser General Public License v3 (LGPLv3)
Classifier: Topic :: Internet
Classifier: Topic :: Communications
Classifier: Topic :: Communications :: Chat
Classifier: Topic :: Software Development :: Libraries
Classifier: Topic :: Software Development :: Libraries :: Python Modules
Classifier: Topic :: Software Development :: Libraries :: Application Frameworks
Requires-Python: ~=3.7
License-File: LICENSE
Requires-Dist: aiohttp
Requires-Dist: pycryptodome
Requires-Dist: aiofiles
Requires-Dist: markdownify
Requires-Dist: mutagen
Provides-Extra: cv
Requires-Dist: opencv-python; extra == "cv"
Provides-Extra: movie
Requires-Dist: numpy; extra == "movie"
Requires-Dist: moviepy; extra == "movie"
Requires-Dist: pillow; extra == "movie"
Provides-Extra: pil
Requires-Dist: pillow; extra == "pil"
Provides-Extra: rtc
Requires-Dist: aiortc; extra == "rtc"
Dynamic: author
Dynamic: author-email
Dynamic: classifier
Dynamic: description
Dynamic: description-content-type
Dynamic: home-page
Dynamic: keywords
Dynamic: license-file
Dynamic: provides-extra
Dynamic: requires-dist
Dynamic: requires-python
Dynamic: summary
